assess_gtfs/__init__.py
assess_gtfs/calendar.py
assess_gtfs/cleaners.py
assess_gtfs/gtfs_utils.py
assess_gtfs/multi_validation.py
assess_gtfs/routes.py
assess_gtfs/validation.py
assess_gtfs/validators.py
assess_gtfs/data/newport-20230613_gtfs.zip
assess_gtfs/data/route_lookup.pkl
assess_gtfs/data/report/.gitkeep
assess_gtfs/data/report/css_styles/styles.css
assess_gtfs/data/report/html_templates/evaluation_template.html
assess_gtfs/data/report/html_templates/stops_template.html
assess_gtfs/data/report/html_templates/summary_template.html
assess_gtfs/data/utils/.gitkeep
assess_gtfs/report/__init__.py
assess_gtfs/report/report_utils.py
assess_gtfs/utils/__init__.py
assess_gtfs/utils/constants.py
assess_gtfs/utils/defence.py
assess_gtfs/utils/io.py
assess_gtfs-0.0.6.dist-info/METADATA
assess_gtfs-0.0.6.dist-info/WHEEL
assess_gtfs-0.0.6.dist-info/licenses/LICENSE
assess_gtfs-0.0.6.dist-info/licenses/LICENSE.note
assess_gtfs-0.0.6.dist-info/RECORD
