Metadata-Version: 2.3
Name: assess-gtfs
Version: 0.0.6
Summary: Inspect & validate General Transit Feed Specification
Project-URL: Repository, https://github.com/datasciencecampus/assess_gtfs
Project-URL: Bug tracker, https://github.com/datasciencecampus/assess_gtfs/issues
Author-email: Data Science Campus <datasciencecampus@ons.gov.uk>
License-File: LICENSE
License-File: LICENSE.note
Classifier: Development Status :: 1 - Planning
Classifier: License :: OSI Approved :: MIT License
Classifier: Operating System :: MacOS
Classifier: Programming Language :: Python :: 3
Classifier: Topic :: Scientific/Engineering :: GIS
Requires-Python: >=3.9
Requires-Dist: beautifulsoup4
Requires-Dist: folium
Requires-Dist: geopandas
Requires-Dist: gtfs-kit==5.2.7
Requires-Dist: haversine
Requires-Dist: kaleido
Requires-Dist: numpy
Requires-Dist: pandas
Requires-Dist: plotly
Requires-Dist: pretty-html-table
Requires-Dist: pyprojroot
Requires-Dist: requests
Requires-Dist: tqdm
Provides-Extra: dev
Requires-Dist: hatch; extra == 'dev'
Provides-Extra: docs
Requires-Dist: ipykernel==6.23.1; extra == 'docs'
Requires-Dist: jupyterlab; extra == 'docs'
Requires-Dist: mapclassify; extra == 'docs'
Requires-Dist: matplotlib; extra == 'docs'
Requires-Dist: nbformat>=4.2.0; extra == 'docs'
Requires-Dist: quartodoc; extra == 'docs'
Provides-Extra: test
Requires-Dist: coverage; extra == 'test'
Requires-Dist: pre-commit; extra == 'test'
Requires-Dist: pytest; extra == 'test'
Requires-Dist: pytest-mock; extra == 'test'
